{
	"id": "c8844793-45f4-45b6-9fc0-3ac25be87c3f",
	"name": "Trello",
	"values": [
		{
			"key": "trelloKey",
			"value": "your trello key",
			"description": {
				"content": "",
				"type": "text/plain"
			},
			"enabled": true
		},
		{
			"key": "trelloToken",
			"value": "your trello token",
			"description": {
				"content": "",
				"type": "text/plain"
			},
			"enabled": true
		}
	],
	"_postman_variable_scope": "environment",
	"_postman_exported_at": "2019-03-22T10:34:09.542Z",
	"_postman_exported_using": "Postman/7.0.6"
}